mobio/libs/abac/__init__.py
mobio/libs/abac/call_api.py
mobio/libs/abac/pdp.py
mobio/libs/abac/result_access.py
mobio/libs/abac/adapter/__init__.py
mobio/libs/abac/adapter/adapter.py
mobio/libs/abac/adapter/elasticsearch_adapter.py
mobio/libs/abac/policy/__init__.py
mobio/libs/abac/policy/exceptions.py
mobio/libs/abac/policy/policy.py
mobio/libs/abac/policy/utils.py
mobio/libs/abac/policy/conditions/__init__.py
mobio/libs/abac/policy/conditions/base.py
mobio/libs/abac/policy/conditions/schema.py
mobio/libs/abac/policy/conditions/boolean/__init__.py
mobio/libs/abac/policy/conditions/boolean/base.py
mobio/libs/abac/policy/conditions/boolean/check_bool.py
mobio/libs/abac/policy/conditions/collection/__init__.py
mobio/libs/abac/policy/conditions/collection/all_in.py
mobio/libs/abac/policy/conditions/collection/all_not_in.py
mobio/libs/abac/policy/conditions/collection/any_in.py
mobio/libs/abac/policy/conditions/collection/any_not_in.py
mobio/libs/abac/policy/conditions/collection/base.py
mobio/libs/abac/policy/conditions/collection/is_empty.py
mobio/libs/abac/policy/conditions/collection/is_in.py
mobio/libs/abac/policy/conditions/collection/is_not_empty.py
mobio/libs/abac/policy/conditions/collection/is_not_in.py
mobio/libs/abac/policy/conditions/date_time/__init__.py
mobio/libs/abac/policy/conditions/date_time/base.py
mobio/libs/abac/policy/conditions/date_time/date_eq.py
mobio/libs/abac/policy/conditions/date_time/date_gt.py
mobio/libs/abac/policy/conditions/date_time/date_gte.py
mobio/libs/abac/policy/conditions/date_time/date_lt.py
mobio/libs/abac/policy/conditions/date_time/date_lte.py
mobio/libs/abac/policy/conditions/date_time/date_neq.py
mobio/libs/abac/policy/conditions/day/__init__.py
mobio/libs/abac/policy/conditions/day/base.py
mobio/libs/abac/policy/conditions/day/day_eq.py
mobio/libs/abac/policy/conditions/day/day_gt.py
mobio/libs/abac/policy/conditions/day/day_gte.py
mobio/libs/abac/policy/conditions/day/day_lt.py
m_abac_anhnt-1.0.6.dist-info/METADATA
m_abac_anhnt-1.0.6.dist-info/WHEEL
m_abac_anhnt-1.0.6.dist-info/top_level.txt
m_abac_anhnt-1.0.6.dist-info/RECORD
